Metadata-Version: 2.1
Name: luis-distributions
Version: 0.1
Summary: Gaussian distributions
